{
  "project_info": {
    "project_number": "407007104181",
    "project_id": "contask-52156",
    "storage_bucket": "contask-52156.firebasestorage.app"
  },
  "client": [
    {
      "client_info": {
        "mobilesdk_app_id": "1:407007104181:android:5deaa18342a8bb50d942fc",
        "android_client_info": {
          "package_name": "com.example.contask"
        }
      },
      "oauth_client": [
        {
          "client_id": "407007104181-u8rjv708urkeds7ndjgblgpm94rmksil.apps.googleusercontent.com",
          "client_type": 3
        }
      ],
      "api_key": [
        {
          "current_key": "AIzaSyByenvoJbzLpxtG8J1omzZ5R1Y4JhVnPK8"
        }
      ],
      "services": {
        "appinvite_service": {
          "other_platform_oauth_client": [
            {
              "client_id": "407007104181-u8rjv708urkeds7ndjgblgpm94rmksil.apps.googleusercontent.com",
              "client_type": 3
            },
            {
              "client_id": "407007104181-4rhd2d3mhu8j35rq9ehbuj3r4lov2jva.apps.googleusercontent.com",
              "client_type": 2,
              "ios_info": {
                "bundle_id": "com.example.contask"
              }
            }
          ]
        }
      }
    },
    {
      "client_info": {
        "mobilesdk_app_id": "1:407007104181:android:78829fafe9143e6dd942fc",
        "android_client_info": {
          "package_name": "com.example.event_task_manager"
        }
      },
      "oauth_client": [
        {
          "client_id": "407007104181-u8rjv708urkeds7ndjgblgpm94rmksil.apps.googleusercontent.com",
          "client_type": 3
        }
      ],
      "api_key": [
        {
          "current_key": "AIzaSyByenvoJbzLpxtG8J1omzZ5R1Y4JhVnPK8"
        }
      ],
      "services": {
        "appinvite_service": {
          "other_platform_oauth_client": [
            {
              "client_id": "407007104181-u8rjv708urkeds7ndjgblgpm94rmksil.apps.googleusercontent.com",
              "client_type": 3
            },
            {
              "client_id": "407007104181-4rhd2d3mhu8j35rq9ehbuj3r4lov2jva.apps.googleusercontent.com",
              "client_type": 2,
              "ios_info": {
                "bundle_id": "com.example.contask"
              }
            }
          ]
        }
      }
    },
    {
      "client_info": {
        "mobilesdk_app_id": "1:407007104181:android:af7c472563cb761dd942fc",
        "android_client_info": {
          "package_name": "com.example.new_contaskcursor"
        }
      },
      "oauth_client": [
        {
          "client_id": "407007104181-u8rjv708urkeds7ndjgblgpm94rmksil.apps.googleusercontent.com",
          "client_type": 3
        }
      ],
      "api_key": [
        {
          "current_key": "AIzaSyByenvoJbzLpxtG8J1omzZ5R1Y4JhVnPK8"
        }
      ],
      "services": {
        "appinvite_service": {
          "other_platform_oauth_client": [
            {
              "client_id": "407007104181-u8rjv708urkeds7ndjgblgpm94rmksil.apps.googleusercontent.com",
              "client_type": 3
            },
            {
              "client_id": "407007104181-4rhd2d3mhu8j35rq9ehbuj3r4lov2jva.apps.googleusercontent.com",
              "client_type": 2,
              "ios_info": {
                "bundle_id": "com.example.contask"
              }
            }
          ]
        }
      }
    },
    {
      "client_info": {
        "mobilesdk_app_id": "1:407007104181:android:e761aae8bcb8debfd942fc",
        "android_client_info": {
          "package_name": "com.tasksevents.tasks_events_manager"
        }
      },
      "oauth_client": [
        {
          "client_id": "407007104181-u8rjv708urkeds7ndjgblgpm94rmksil.apps.googleusercontent.com",
          "client_type": 3
        }
      ],
      "api_key": [
        {
          "current_key": "AIzaSyByenvoJbzLpxtG8J1omzZ5R1Y4JhVnPK8"
        }
      ],
      "services": {
        "appinvite_service": {
          "other_platform_oauth_client": [
            {
              "client_id": "407007104181-u8rjv708urkeds7ndjgblgpm94rmksil.apps.googleusercontent.com",
              "client_type": 3
            },
            {
              "client_id": "407007104181-4rhd2d3mhu8j35rq9ehbuj3r4lov2jva.apps.googleusercontent.com",
              "client_type": 2,
              "ios_info": {
                "bundle_id": "com.example.contask"
              }
            }
          ]
        }
      }
    }
  ],
  "configuration_version": "1"
}